{"nodes": [{"id": "{vfprintf}", "data": {"macke_bug_chain_length": 0, "distance_to_interface": 1, "clustering_coefficient": 0.26666666666666666, "node_degree": [1, 5, 6], "faulty": false, "macke_vulnerabilities_found": 0, "node_path_length": 1.0}, "type": 0.0}, {"id": "{zpaq_compress}", "data": {"macke_bug_chain_length": 0, "distance_to_interface": 1, "clustering_coefficient": 0.0, "node_degree": [1, 2, 3], "faulty": false, "macke_vulnerabilities_found": 0, "node_path_length": 1.0}, "type": 0.0}, {"id": "{read_buf}", "data": {"macke_bug_chain_length": 19, "distance_to_interface": 2, "faulty": true, "clustering_coefficient": 0.15555555555555556, "node_degree": [4, 6, 10], "cvss3": {"scope": "UNCHANGED", "userInteraction": "REQUIRED", "attackVector": "LOCAL", "attackComplexity": "LOW", "privilegesRequired": "NONE", "integrityImpact": "HIGH", "availabilityImpact": "HIGH", "vectorString": "AV:L/AC:L/PR:N/UI:R/S:U/C:H/I:H/A:H", "baseSeverity": "HIGH", "baseScore": 7.8, "confidentialityImpact": "HIGH"}, "macke_vulnerabilities_found": 1, "node_path_length": 2.1893004115226335}, "type": 999}, {"id": "{bzip2_compress_buf}", "data": {"macke_bug_chain_length": 1, "distance_to_interface": 2, "cvss3": {"scope": "UNCHANGED", "predicted": true, "attackVector": "NETWORK", "privilegesRequired": "NONE", "availabilityImpact": "HIGH", "baseSeverity": "High", "baseScore": 8.1, "userInteraction": "REQUIRED", "attackComplexity": "LOW", "integrityImpact": "NONE", "vectorString": "AV:N/AC:L/PR:N/UI:R/S:U/C:H/I:N/A:H", "confidentialityImpact": "HIGH"}, "clustering_coefficient": 0.3611111111111111, "node_degree": [7, 2, 9], "faulty": true, "macke_vulnerabilities_found": 1, "node_path_length": 1.3125}, "type": 6.5}, {"id": "{cksem_init}", "data": {"macke_bug_chain_length": 1, "distance_to_interface": 2, "cvss3": {"scope": "UNCHANGED", "predicted": true, "attackVector": "NETWORK", "privilegesRequired": "NONE", "availabilityImpact": "HIGH", "baseSeverity": "Medium", "baseScore": 6.5, "userInteraction": "REQUIRED", "attackComplexity": "LOW", "integrityImpact": "NONE", "vectorString": "AV:N/AC:L/PR:N/UI:R/S:U/C:N/I:N/A:H", "confidentialityImpact": "NONE"}, "clustering_coefficient": 0.16666666666666666, "node_degree": [3, 1, 4], "faulty": true, "macke_vulnerabilities_found": 1, "node_path_length": 1.0}, "type": 1.3333333333333333}, {"id": "{__errno_location}", "data": {"macke_bug_chain_length": 0, "distance_to_interface": 1, "clustering_coefficient": 0.0, "node_degree": [1, 6, 7], "faulty": false, "macke_vulnerabilities_found": 0, "node_path_length": 1.0}, "type": 0.0}, {"id": "{getchar}", "data": {"macke_bug_chain_length": 0, "distance_to_interface": 1, "clustering_coefficient": 0.0, "node_degree": [1, 2, 3], "faulty": false, "macke_vulnerabilities_found": 0, "node_path_length": 1.0}, "type": 0.0}, {"id": "{print_stuff}", "data": {"macke_bug_chain_length": 19, "distance_to_interface": 2, "cvss3": {"scope": "UNCHANGED", "predicted": true, "attackVector": "LOCAL", "privilegesRequired": "NONE", "availabilityImpact": "HIGH", "baseSeverity": "Medium", "baseScore": 5.5, "userInteraction": "REQUIRED", "attackComplexity": "LOW", "integrityImpact": "NONE", "vectorString": "AV:L/AC:L/PR:N/UI:R/S:U/C:N/I:N/A:H", "confidentialityImpact": "NONE"}, "clustering_coefficient": 0.08088235294117647, "node_degree": [3, 14, 17], "faulty": true, "macke_vulnerabilities_found": 1, "node_path_length": 0}, "type": 52.25}, {"id": "{llvm.memset.p0i8.i64}", "data": {"macke_bug_chain_length": 0, "distance_to_interface": 1, "clustering_coefficient": 0, "node_degree": [0, 1, 1], "faulty": false, "macke_vulnerabilities_found": 0, "node_path_length": 0}, "type": 0}, {"id": "{fill_buffer}", "data": {"macke_bug_chain_length": 2, "distance_to_interface": 2, "cvss3": {"scope": "UNCHANGED", "predicted": true, "attackVector": "LOCAL", "privilegesRequired": "NONE", "availabilityImpact": "HIGH", "baseSeverity": "High", "baseScore": 8.4, "userInteraction": "NONE", "attackComplexity": "LOW", "integrityImpact": "HIGH", "vectorString": "AV:L/AC:L/PR:N/UI:N/S:U/C:H/I:H/A:H", "confidentialityImpact": "HIGH"}, "clustering_coefficient": 0.05263157894736842, "node_degree": [19, 1, 20], "faulty": true, "macke_vulnerabilities_found": 1, "node_path_length": 2.9248615259101807}, "type": 4.2105263157894735}, {"id": "{pthread_detach}", "data": {"macke_bug_chain_length": 0, "distance_to_interface": 1, "clustering_coefficient": 0.3333333333333333, "node_degree": [1, 2, 3], "faulty": false, "macke_vulnerabilities_found": 0, "node_path_length": 1.0}, "type": 0.0}, {"id": "{lock_mutex}", "data": {"macke_bug_chain_length": 1, "distance_to_interface": 1, "cvss3": {"scope": "UNCHANGED", "predicted": true, "attackVector": "LOCAL", "privilegesRequired": "NONE", "availabilityImpact": "HIGH", "baseSeverity": "Medium", "baseScore": 6.2, "userInteraction": "NONE", "attackComplexity": "LOW", "integrityImpact": "NONE", "vectorString": "AV:L/AC:L/PR:N/UI:N/S:U/C:N/I:N/A:H", "confidentialityImpact": "NONE"}, "clustering_coefficient": 0.2857142857142857, "node_degree": [2, 5, 7], "faulty": true, "macke_vulnerabilities_found": 1, "node_path_length": 1.5}, "type": 2.0}, {"id": "{read_stream}", "data": {"macke_bug_chain_length": 1, "distance_to_interface": 1, "cvss3": {"scope": "UNCHANGED", "predicted": true, "attackVector": "NETWORK", "privilegesRequired": "NONE", "availabilityImpact": "HIGH", "baseSeverity": "Critical", "baseScore": 9.8, "userInteraction": "NONE", "attackComplexity": "LOW", "integrityImpact": "HIGH", "vectorString": "AV:N/AC:L/PR:N/UI:N/S:U/C:H/I:H/A:H", "confidentialityImpact": "HIGH"}, "clustering_coefficient": 0.0, "node_degree": [1, 1, 2], "faulty": true, "macke_vulnerabilities_found": 1, "node_path_length": 3.9248615259101807}, "type": 0.0}, {"id": "{cksem_post}", "data": {"macke_bug_chain_length": 1, "distance_to_interface": 2, "cvss3": {"scope": "UNCHANGED", "predicted": true, "attackVector": "LOCAL", "privilegesRequired": "NONE", "availabilityImpact": "HIGH", "baseSeverity": "Medium", "baseScore": 5.5, "userInteraction": "REQUIRED", "attackComplexity": "LOW", "integrityImpact": "NONE", "vectorString": "AV:L/AC:L/PR:N/UI:R/S:U/C:N/I:N/A:H", "confidentialityImpact": "NONE"}, "clustering_coefficient": 0.14285714285714285, "node_degree": [3, 4, 7], "faulty": true, "macke_vulnerabilities_found": 1, "node_path_length": 1.25}, "type": 2.0}, {"id": "{ucompthread}", "data": {"macke_bug_chain_length": 1, "distance_to_interface": 1, "cvss3": {"scope": "UNCHANGED", "predicted": true, "attackVector": "LOCAL", "privilegesRequired": "NONE", "availabilityImpact": "HIGH", "baseSeverity": "Medium", "baseScore": 6.2, "userInteraction": "NONE", "attackComplexity": "LOW", "integrityImpact": "NONE", "vectorString": "AV:L/AC:L/PR:N/UI:N/S:U/C:N/I:N/A:H", "confidentialityImpact": "NONE"}, "clustering_coefficient": 0.15384615384615385, "node_degree": [13, 1, 14], "faulty": true, "macke_vulnerabilities_found": 1, "node_path_length": 2.199314187741106}, "type": 2.153846153846154}, {"id": "{write_val}", "data": {"macke_bug_chain_length": 1, "distance_to_interface": 2, "cvss3": {"scope": "UNCHANGED", "predicted": true, "attackVector": "NETWORK", "privilegesRequired": "NONE", "availabilityImpact": "HIGH", "baseSeverity": "Critical", "baseScore": 9.8, "userInteraction": "NONE", "attackComplexity": "LOW", "integrityImpact": "HIGH", "vectorString": "AV:N/AC:L/PR:N/UI:N/S:U/C:H/I:H/A:H", "confidentialityImpact": "HIGH"}, "clustering_coefficient": 1.0, "node_degree": [1, 1, 2], "faulty": true, "macke_vulnerabilities_found": 1, "node_path_length": 1.0}, "type": 4.0}, {"id": "{lzo_compresses}", "data": {"macke_bug_chain_length": 1, "distance_to_interface": 3, "cvss3": {"scope": "UNCHANGED", "predicted": true, "attackVector": "LOCAL", "privilegesRequired": "NONE", "availabilityImpact": "HIGH", "baseSeverity": "Medium", "baseScore": 5.5, "userInteraction": "REQUIRED", "attackComplexity": "LOW", "integrityImpact": "NONE", "vectorString": "AV:L/AC:L/PR:N/UI:R/S:U/C:N/I:N/A:H", "confidentialityImpact": "NONE"}, "clustering_coefficient": 0.35714285714285715, "node_degree": [5, 3, 8], "faulty": true, "macke_vulnerabilities_found": 1, "node_path_length": 1.0}, "type": 8.571428571428571}, {"id": "{llvm.va_start}", "data": {"macke_bug_chain_length": 0, "distance_to_interface": 1, "clustering_coefficient": 0, "node_degree": [0, 1, 1], "faulty": false, "macke_vulnerabilities_found": 0, "node_path_length": 0}, "type": 0}, {"id": "{compress2}", "data": {"macke_bug_chain_length": 0, "distance_to_interface": 1, "clustering_coefficient": 0.0, "node_degree": [1, 2, 3], "faulty": false, "macke_vulnerabilities_found": 0, "node_path_length": 1.0}, "type": 0.0}, {"id": "{free}", "data": {"macke_bug_chain_length": 0, "distance_to_interface": 1, "clustering_coefficient": 0.09523809523809523, "node_degree": [1, 21, 22], "faulty": false, "macke_vulnerabilities_found": 0, "node_path_length": 1.0}, "type": 0.0}, {"id": "{write}", "data": {"macke_bug_chain_length": 0, "distance_to_interface": 1, "clustering_coefficient": 0.3333333333333333, "node_degree": [1, 2, 3], "faulty": false, "macke_vulnerabilities_found": 0, "node_path_length": 1.0}, "type": 0.0}, {"id": "{create_pthread}", "data": {"macke_bug_chain_length": 0, "distance_to_interface": 1, "clustering_coefficient": 0.2, "node_degree": [2, 3, 5], "faulty": false, "macke_vulnerabilities_found": 0, "node_path_length": 1.0}, "type": 0.0}, {"id": "{flush_buffer}", "data": {"macke_bug_chain_length": 1, "distance_to_interface": 1, "cvss3": {"scope": "UNCHANGED", "predicted": true, "attackVector": "NETWORK", "privilegesRequired": "NONE", "availabilityImpact": "HIGH", "baseSeverity": "Critical", "baseScore": 9.1, "userInteraction": "NONE", "attackComplexity": "LOW", "integrityImpact": "NONE", "vectorString": "AV:N/AC:L/PR:N/UI:N/S:U/C:H/I:N/A:H", "confidentialityImpact": "HIGH"}, "clustering_coefficient": 0.3333333333333333, "node_degree": [1, 2, 3], "faulty": true, "macke_vulnerabilities_found": 1, "node_path_length": 2.5}, "type": 1.0}, {"id": "{read_u8}", "data": {"macke_bug_chain_length": 5, "distance_to_interface": 2, "cvss3": {"scope": "UNCHANGED", "predicted": true, "attackVector": "LOCAL", "privilegesRequired": "NONE", "availabilityImpact": "HIGH", "baseSeverity": "Medium", "baseScore": 6.3, "userInteraction": "REQUIRED", "attackComplexity": "HIGH", "integrityImpact": "HIGH", "vectorString": "AV:L/AC:H/PR:N/UI:R/S:U/C:N/I:H/A:H", "confidentialityImpact": "NONE"}, "clustering_coefficient": 0.6666666666666666, "node_degree": [1, 2, 3], "faulty": true, "macke_vulnerabilities_found": 1, "node_path_length": 1.0}, "type": 20.0}, {"id": "{pthread_mutex_lock}", "data": {"macke_bug_chain_length": 0, "distance_to_interface": 1, "clustering_coefficient": 0.3333333333333333, "node_degree": [1, 2, 3], "faulty": false, "macke_vulnerabilities_found": 0, "node_path_length": 1.0}, "type": 0.0}, {"id": "{zpaq_compress_buf}", "data": {"macke_bug_chain_length": 1, "distance_to_interface": 2, "cvss3": {"scope": "UNCHANGED", "predicted": true, "attackVector": "LOCAL", "privilegesRequired": "NONE", "availabilityImpact": "HIGH", "baseSeverity": "Medium", "baseScore": 5.5, "userInteraction": "REQUIRED", "attackComplexity": "LOW", "integrityImpact": "NONE", "vectorString": "AV:L/AC:L/PR:N/UI:R/S:U/C:N/I:N/A:H", "confidentialityImpact": "NONE"}, "clustering_coefficient": 0.21428571428571427, "node_degree": [7, 1, 8], "faulty": true, "macke_vulnerabilities_found": 1, "node_path_length": 1.0}, "type": 3.4285714285714284}, {"id": "{sem_post}", "data": {"macke_bug_chain_length": 0, "distance_to_interface": 1, "clustering_coefficient": 0.0, "node_degree": [1, 2, 3], "faulty": false, "macke_vulnerabilities_found": 0, "node_path_length": 1.0}, "type": 0.0}, {"id": "{read_tmpinfile}", "data": {"macke_bug_chain_length": 0, "distance_to_interface": 1, "clustering_coefficient": 0.0, "node_degree": [1, 2, 3], "faulty": false, "macke_vulnerabilities_found": 0, "node_path_length": 1.0}, "type": 0.0}, {"id": "{read_val}", "data": {"macke_bug_chain_length": 5, "distance_to_interface": 2, "cvss3": {"scope": "UNCHANGED", "predicted": true, "attackVector": "LOCAL", "privilegesRequired": "NONE", "availabilityImpact": "LOW", "baseSeverity": "Medium", "baseScore": 5.3, "userInteraction": "REQUIRED", "attackComplexity": "HIGH", "integrityImpact": "HIGH", "vectorString": "AV:L/AC:H/PR:N/UI:R/S:U/C:N/I:H/A:L", "confidentialityImpact": "NONE"}, "clustering_coefficient": 0.6666666666666666, "node_degree": [1, 2, 3], "faulty": true, "macke_vulnerabilities_found": 1, "node_path_length": 3.1893004115226335}, "type": 20.0}, {"id": "{BZ2_bzBuffToBuffCompress}", "data": {"macke_bug_chain_length": 0, "distance_to_interface": 1, "clustering_coefficient": 0.0, "node_degree": [1, 2, 3], "faulty": false, "macke_vulnerabilities_found": 0, "node_path_length": 1.0}, "type": 0.0}, {"id": "{cksem_wait}", "data": {"macke_bug_chain_length": 1, "distance_to_interface": 2, "cvss3": {"scope": "UNCHANGED", "predicted": true, "attackVector": "LOCAL", "privilegesRequired": "NONE", "availabilityImpact": "HIGH", "baseSeverity": "High", "baseScore": 7.8, "userInteraction": "REQUIRED", "attackComplexity": "LOW", "integrityImpact": "HIGH", "vectorString": "AV:L/AC:L/PR:N/UI:R/S:U/C:H/I:H/A:H", "confidentialityImpact": "HIGH"}, "clustering_coefficient": 0.06666666666666667, "node_degree": [3, 3, 6], "faulty": true, "macke_vulnerabilities_found": 1, "node_path_length": 1.25}, "type": 0.8}, {"id": "{lzma_compress_buf}", "data": {"macke_bug_chain_length": 1, "distance_to_interface": 2, "cvss3": {"scope": "UNCHANGED", "predicted": true, "attackVector": "LOCAL", "privilegesRequired": "NONE", "availabilityImpact": "HIGH", "baseSeverity": "Medium", "baseScore": 5.5, "userInteraction": "REQUIRED", "attackComplexity": "LOW", "integrityImpact": "NONE", "vectorString": "AV:L/AC:L/PR:N/UI:R/S:U/C:N/I:N/A:H", "confidentialityImpact": "NONE"}, "clustering_coefficient": 0.2727272727272727, "node_degree": [10, 1, 11], "faulty": true, "macke_vulnerabilities_found": 1, "node_path_length": 1.0}, "type": 6.0}, {"id": "{lzo_compress_buf}", "data": {"macke_bug_chain_length": 1, "distance_to_interface": 2, "cvss3": {"scope": "UNCHANGED", "predicted": true, "attackVector": "LOCAL", "privilegesRequired": "NONE", "availabilityImpact": "HIGH", "baseSeverity": "High", "baseScore": 7.1, "userInteraction": "REQUIRED", "attackComplexity": "LOW", "integrityImpact": "NONE", "vectorString": "AV:L/AC:L/PR:N/UI:R/S:U/C:H/I:N/A:H", "confidentialityImpact": "HIGH"}, "clustering_coefficient": 0.10714285714285714, "node_degree": [7, 1, 8], "faulty": true, "macke_vulnerabilities_found": 1, "node_path_length": 1.0}, "type": 1.7142857142857142}, {"id": "{pthread_mutex_init}", "data": {"macke_bug_chain_length": 0, "distance_to_interface": 1, "clustering_coefficient": 0.3333333333333333, "node_degree": [1, 2, 3], "faulty": false, "macke_vulnerabilities_found": 0, "node_path_length": 1.0}, "type": 0.0}, {"id": "{lrz_encrypt}", "data": {"macke_bug_chain_length": 1, "distance_to_interface": 2, "cvss3": {"scope": "UNCHANGED", "predicted": true, "attackVector": "NETWORK", "privilegesRequired": "NONE", "availabilityImpact": "HIGH", "baseSeverity": "Critical", "baseScore": 9.1, "userInteraction": "NONE", "attackComplexity": "LOW", "integrityImpact": "NONE", "vectorString": "AV:N/AC:L/PR:N/UI:N/S:U/C:H/I:N/A:H", "confidentialityImpact": "HIGH"}, "clustering_coefficient": 0.3333333333333333, "node_degree": [1, 2, 3], "faulty": true, "macke_vulnerabilities_found": 1, "node_path_length": 1.0}, "type": 2.0}, {"id": "{realloc}", "data": {"macke_bug_chain_length": 0, "distance_to_interface": 1, "clustering_coefficient": 0.3333333333333333, "node_degree": [1, 3, 4], "faulty": false, "macke_vulnerabilities_found": 0, "node_path_length": 1.0}, "type": 0.0}, {"id": "{zpaq_decompress}", "data": {"macke_bug_chain_length": 0, "distance_to_interface": 1, "clustering_coefficient": 0.0, "node_degree": [1, 2, 3], "faulty": false, "macke_vulnerabilities_found": 0, "node_path_length": 1.0}, "type": 0.0}, {"id": "{write_magic}", "data": {"macke_bug_chain_length": 0, "distance_to_interface": 1, "clustering_coefficient": 0.3333333333333333, "node_degree": [1, 2, 3], "faulty": false, "macke_vulnerabilities_found": 0, "node_path_length": 1.0}, "type": 0.0}, {"id": "{LzmaUncompress}", "data": {"macke_bug_chain_length": 0, "distance_to_interface": 1, "clustering_coefficient": 0.0, "node_degree": [1, 2, 3], "faulty": false, "macke_vulnerabilities_found": 0, "node_path_length": 1.0}, "type": 0.0}, {"id": "{flush_tmpoutbuf}", "data": {"macke_bug_chain_length": 0, "distance_to_interface": 1, "clustering_coefficient": 0.3333333333333333, "node_degree": [1, 2, 3], "faulty": false, "macke_vulnerabilities_found": 0, "node_path_length": 1.0}, "type": 0.0}, {"id": "{read_fdin}", "data": {"macke_bug_chain_length": 1, "distance_to_interface": 4, "cvss3": {"scope": "UNCHANGED", "predicted": true, "attackVector": "LOCAL", "privilegesRequired": "NONE", "availabilityImpact": "HIGH", "baseSeverity": "Medium", "baseScore": 6.2, "userInteraction": "NONE", "attackComplexity": "LOW", "integrityImpact": "NONE", "vectorString": "AV:L/AC:L/PR:N/UI:N/S:U/C:N/I:N/A:H", "confidentialityImpact": "NONE"}, "clustering_coefficient": 0.16666666666666666, "node_degree": [2, 2, 4], "faulty": true, "macke_vulnerabilities_found": 1, "node_path_length": 1.5}, "type": 2.6666666666666665}, {"id": "{lseek}", "data": {"macke_bug_chain_length": 0, "distance_to_interface": 1, "clustering_coefficient": 0.1, "node_degree": [1, 4, 5], "faulty": false, "macke_vulnerabilities_found": 0, "node_path_length": 1.0}, "type": 0.0}, {"id": "{close_stream_out}", "data": {"macke_bug_chain_length": 1, "distance_to_interface": 1, "cvss3": {"scope": "UNCHANGED", "predicted": true, "attackVector": "LOCAL", "privilegesRequired": "NONE", "availabilityImpact": "HIGH", "baseSeverity": "High", "baseScore": 7.1, "userInteraction": "REQUIRED", "attackComplexity": "LOW", "integrityImpact": "NONE", "vectorString": "AV:L/AC:L/PR:N/UI:R/S:U/C:H/I:N/A:H", "confidentialityImpact": "HIGH"}, "clustering_coefficient": 0.14285714285714285, "node_degree": [7, 1, 8], "faulty": true, "macke_vulnerabilities_found": 1, "node_path_length": 1.7414829659318638}, "type": 1.1428571428571428}, {"id": "{zpaq_decompress_buf}", "data": {"macke_bug_chain_length": 1, "distance_to_interface": 2, "cvss3": {"scope": "UNCHANGED", "predicted": true, "attackVector": "LOCAL", "privilegesRequired": "NONE", "availabilityImpact": "HIGH", "baseSeverity": "High", "baseScore": 7.1, "userInteraction": "REQUIRED", "attackComplexity": "LOW", "integrityImpact": "HIGH", "vectorString": "AV:L/AC:L/PR:N/UI:R/S:U/C:N/I:H/A:H", "confidentialityImpact": "NONE"}, "clustering_coefficient": 0.13333333333333333, "node_degree": [5, 1, 6], "faulty": true, "macke_vulnerabilities_found": 1, "node_path_length": 1.2}, "type": 1.6}, {"id": "{cond_wait}", "data": {"macke_bug_chain_length": 1, "distance_to_interface": 2, "cvss3": {"scope": "UNCHANGED", "predicted": true, "attackVector": "NETWORK", "privilegesRequired": "NONE", "availabilityImpact": "HIGH", "baseSeverity": "Medium", "baseScore": 6.5, "userInteraction": "REQUIRED", "attackComplexity": "LOW", "integrityImpact": "NONE", "vectorString": "AV:N/AC:L/PR:N/UI:R/S:U/C:N/I:N/A:H", "confidentialityImpact": "NONE"}, "clustering_coefficient": 0.16666666666666666, "node_degree": [2, 2, 4], "faulty": true, "macke_vulnerabilities_found": 1, "node_path_length": 1.3333333333333333}, "type": 1.3333333333333333}, {"id": "{fatal}", "data": {"macke_bug_chain_length": 1, "distance_to_interface": 2, "cvss3": {"scope": "UNCHANGED", "predicted": true, "attackVector": "LOCAL", "privilegesRequired": "NONE", "availabilityImpact": "HIGH", "baseSeverity": "High", "baseScore": 7.8, "userInteraction": "REQUIRED", "attackComplexity": "LOW", "integrityImpact": "HIGH", "vectorString": "AV:L/AC:L/PR:N/UI:R/S:U/C:H/I:H/A:H", "confidentialityImpact": "HIGH"}, "clustering_coefficient": 0.07246376811594203, "node_degree": [4, 20, 24], "faulty": true, "macke_vulnerabilities_found": 1, "node_path_length": 1.6363636363636365}, "type": 3.4782608695652177}, {"id": "{lzo1x_decompress}", "data": {"macke_bug_chain_length": 0, "distance_to_interface": 1, "clustering_coefficient": 0.0, "node_degree": [1, 2, 3], "faulty": false, "macke_vulnerabilities_found": 0, "node_path_length": 1.0}, "type": 0.0}, {"id": "{write_buf}", "data": {"macke_bug_chain_length": 1, "distance_to_interface": 2, "cvss3": {"scope": "UNCHANGED", "predicted": true, "attackVector": "LOCAL", "privilegesRequired": "NONE", "availabilityImpact": "HIGH", "baseSeverity": "Medium", "baseScore": 5.5, "userInteraction": "REQUIRED", "attackComplexity": "LOW", "integrityImpact": "NONE", "vectorString": "AV:L/AC:L/PR:N/UI:R/S:U/C:N/I:N/A:H", "confidentialityImpact": "NONE"}, "clustering_coefficient": 0.14285714285714285, "node_degree": [4, 4, 8], "faulty": true, "macke_vulnerabilities_found": 1, "node_path_length": 1.2}, "type": 2.2857142857142856}, {"id": "{init_mutex}", "data": {"macke_bug_chain_length": 1, "distance_to_interface": 1, "cvss3": {"scope": "UNCHANGED", "predicted": true, "attackVector": "NETWORK", "privilegesRequired": "NONE", "availabilityImpact": "HIGH", "baseSeverity": "Critical", "baseScore": 9.8, "userInteraction": "NONE", "attackComplexity": "LOW", "integrityImpact": "HIGH", "vectorString": "AV:N/AC:L/PR:N/UI:N/S:U/C:H/I:H/A:H", "confidentialityImpact": "HIGH"}, "clustering_coefficient": 0.3333333333333333, "node_degree": [2, 1, 3], "faulty": true, "macke_vulnerabilities_found": 1, "node_path_length": 1.0}, "type": 1.0}, {"id": "{write_fdin}", "data": {"macke_bug_chain_length": 0, "distance_to_interface": 1, "clustering_coefficient": 0.0, "node_degree": [1, 2, 3], "faulty": false, "macke_vulnerabilities_found": 0, "node_path_length": 1.0}, "type": 0.0}, {"id": "{write_1g}", "data": {"macke_bug_chain_length": 1, "distance_to_interface": 1, "cvss3": {"scope": "UNCHANGED", "predicted": true, "attackVector": "NETWORK", "privilegesRequired": "NONE", "availabilityImpact": "HIGH", "baseSeverity": "Critical", "baseScore": 9.8, "userInteraction": "NONE", "attackComplexity": "LOW", "integrityImpact": "HIGH", "vectorString": "AV:N/AC:L/PR:N/UI:N/S:U/C:H/I:H/A:H", "confidentialityImpact": "HIGH"}, "clustering_coefficient": 0.3333333333333333, "node_degree": [1, 2, 3], "faulty": true, "macke_vulnerabilities_found": 1, "node_path_length": 1.0}, "type": 1.0}, {"id": "{llvm.dbg.declare}", "data": {"macke_bug_chain_length": 0, "distance_to_interface": 1, "clustering_coefficient": 0, "node_degree": [0, 1, 1], "faulty": false, "macke_vulnerabilities_found": 0, "node_path_length": 0}, "type": 0}, {"id": "{round_up_page}", "data": {"macke_bug_chain_length": 0, "distance_to_interface": 1, "clustering_coefficient": 0.015151515151515152, "node_degree": [1, 11, 12], "faulty": false, "macke_vulnerabilities_found": 0, "node_path_length": 1.0}, "type": 0.0}, {"id": "{LzmaCompress}", "data": {"macke_bug_chain_length": 0, "distance_to_interface": 1, "clustering_coefficient": 0.0, "node_degree": [1, 2, 3], "faulty": false, "macke_vulnerabilities_found": 0, "node_path_length": 1.0}, "type": 0.0}, {"id": "{fd_seekto}", "data": {"macke_bug_chain_length": 1, "distance_to_interface": 4, "cvss3": {"scope": "UNCHANGED", "predicted": true, "attackVector": "NETWORK", "privilegesRequired": "NONE", "availabilityImpact": "HIGH", "baseSeverity": "High", "baseScore": 7.5, "userInteraction": "NONE", "attackComplexity": "LOW", "integrityImpact": "NONE", "vectorString": "AV:N/AC:L/PR:N/UI:N/S:U/C:N/I:N/A:H", "confidentialityImpact": "NONE"}, "clustering_coefficient": 0.3333333333333333, "node_degree": [2, 2, 4], "faulty": true, "macke_vulnerabilities_found": 1, "node_path_length": 1.3333333333333333}, "type": 5.333333333333333}, {"id": "{lzo1x_1_compress}", "data": {"macke_bug_chain_length": 0, "distance_to_interface": 1, "clustering_coefficient": 0.0, "node_degree": [1, 3, 4], "faulty": false, "macke_vulnerabilities_found": 0, "node_path_length": 1.0}, "type": 0.0}, {"id": "{seekto}", "data": {"macke_bug_chain_length": 1, "distance_to_interface": 2, "cvss3": {"scope": "UNCHANGED", "predicted": true, "attackVector": "NETWORK", "privilegesRequired": "NONE", "availabilityImpact": "HIGH", "baseSeverity": "Critical", "baseScore": 9.8, "userInteraction": "NONE", "attackComplexity": "LOW", "integrityImpact": "HIGH", "vectorString": "AV:N/AC:L/PR:N/UI:N/S:U/C:H/I:H/A:H", "confidentialityImpact": "HIGH"}, "clustering_coefficient": 0.5, "node_degree": [2, 2, 4], "faulty": true, "macke_vulnerabilities_found": 1, "node_path_length": 1.0}, "type": 4.0}, {"id": "{decrypt_header}", "data": {"macke_bug_chain_length": 5, "distance_to_interface": 2, "cvss3": {"scope": "UNCHANGED", "predicted": true, "attackVector": "LOCAL", "privilegesRequired": "NONE", "availabilityImpact": "HIGH", "baseSeverity": "High", "baseScore": 7.1, "userInteraction": "REQUIRED", "attackComplexity": "LOW", "integrityImpact": "HIGH", "vectorString": "AV:L/AC:L/PR:N/UI:R/S:U/C:N/I:H/A:H", "confidentialityImpact": "NONE"}, "clustering_coefficient": 0.3333333333333333, "node_degree": [1, 2, 3], "faulty": true, "macke_vulnerabilities_found": 1, "node_path_length": 1.0}, "type": 10.0}, {"id": "{strerror}", "data": {"macke_bug_chain_length": 0, "distance_to_interface": 1, "clustering_coefficient": 0.0, "node_degree": [1, 3, 4], "faulty": false, "macke_vulnerabilities_found": 0, "node_path_length": 1.0}, "type": 0.0}, {"id": "{write_stream}", "data": {"macke_bug_chain_length": 1, "distance_to_interface": 1, "cvss3": {"scope": "UNCHANGED", "predicted": true, "attackVector": "NETWORK", "privilegesRequired": "NONE", "availabilityImpact": "HIGH", "baseSeverity": "High", "baseScore": 8.1, "userInteraction": "NONE", "attackComplexity": "HIGH", "integrityImpact": "HIGH", "vectorString": "AV:N/AC:H/PR:N/UI:N/S:U/C:H/I:H/A:H", "confidentialityImpact": "HIGH"}, "clustering_coefficient": 1.0, "node_degree": [1, 1, 2], "faulty": true, "macke_vulnerabilities_found": 1, "node_path_length": 1.0}, "type": 2.0}, {"id": "{get_seek}", "data": {"macke_bug_chain_length": 1, "distance_to_interface": 2, "cvss3": {"scope": "UNCHANGED", "predicted": true, "attackVector": "NETWORK", "privilegesRequired": "NONE", "availabilityImpact": "HIGH", "baseSeverity": "Critical", "baseScore": 9.8, "userInteraction": "NONE", "attackComplexity": "LOW", "integrityImpact": "HIGH", "vectorString": "AV:N/AC:L/PR:N/UI:N/S:U/C:H/I:H/A:H", "confidentialityImpact": "HIGH"}, "clustering_coefficient": 0.5, "node_degree": [2, 2, 4], "faulty": true, "macke_vulnerabilities_found": 1, "node_path_length": 1.0}, "type": 4.0}, {"id": "{pthread_join}", "data": {"macke_bug_chain_length": 0, "distance_to_interface": 1, "clustering_coefficient": 0.3333333333333333, "node_degree": [1, 2, 3], "faulty": false, "macke_vulnerabilities_found": 0, "node_path_length": 1.0}, "type": 0.0}, {"id": "{fflush}", "data": {"macke_bug_chain_length": 0, "distance_to_interface": 1, "clustering_coefficient": 0.3333333333333333, "node_degree": [1, 3, 4], "faulty": false, "macke_vulnerabilities_found": 0, "node_path_length": 1.0}, "type": 0.0}, {"id": "{setpriority}", "data": {"macke_bug_chain_length": 0, "distance_to_interface": 1, "clustering_coefficient": 0.3333333333333333, "node_degree": [1, 3, 4], "faulty": false, "macke_vulnerabilities_found": 0, "node_path_length": 1.0}, "type": 0.0}, {"id": "{join_pthread}", "data": {"macke_bug_chain_length": 0, "distance_to_interface": 1, "faulty": true, "clustering_coefficient": 0.3333333333333333, "node_degree": [2, 2, 4], "cvss3": {"scope": "UNCHANGED", "userInteraction": "REQUIRED", "attackVector": "LOCAL", "attackComplexity": "LOW", "privilegesRequired": "NONE", "integrityImpact": "NONE", "availabilityImpact": "HIGH", "vectorString": "AV:L/AC:L/PR:N/UI:R/S:U/C:N/I:N/A:H", "baseSeverity": "MEDIUM", "baseScore": 5.5, "confidentialityImpact": "NONE"}, "macke_vulnerabilities_found": 0, "node_path_length": 2.5}, "type": 999}, {"id": "{BZ2_bzBuffToBuffDecompress}", "data": {"macke_bug_chain_length": 0, "distance_to_interface": 1, "clustering_coefficient": 0.0, "node_degree": [1, 2, 3], "faulty": false, "macke_vulnerabilities_found": 0, "node_path_length": 1.0}, "type": 0.0}, {"id": "{lrz_decrypt}", "data": {"macke_bug_chain_length": 1, "distance_to_interface": 3, "cvss3": {"scope": "UNCHANGED", "predicted": true, "attackVector": "NETWORK", "privilegesRequired": "NONE", "availabilityImpact": "HIGH", "baseSeverity": "Medium", "baseScore": 5.9, "userInteraction": "NONE", "attackComplexity": "HIGH", "integrityImpact": "NONE", "vectorString": "AV:N/AC:H/PR:N/UI:N/S:U/C:N/I:N/A:H", "confidentialityImpact": "NONE"}, "clustering_coefficient": 0.3333333333333333, "node_degree": [1, 2, 3], "faulty": true, "macke_vulnerabilities_found": 1, "node_path_length": 2.0}, "type": 3.0}, {"id": "{pthread_create}", "data": {"macke_bug_chain_length": 0, "distance_to_interface": 1, "clustering_coefficient": 0.3333333333333333, "node_degree": [1, 2, 3], "faulty": false, "macke_vulnerabilities_found": 0, "node_path_length": 1.0}, "type": 0.0}, {"id": "{read_u32}", "data": {"macke_bug_chain_length": 5, "distance_to_interface": 2, "cvss3": {"scope": "UNCHANGED", "predicted": true, "attackVector": "LOCAL", "privilegesRequired": "NONE", "availabilityImpact": "HIGH", "baseSeverity": "Medium", "baseScore": 6.3, "userInteraction": "REQUIRED", "attackComplexity": "HIGH", "integrityImpact": "HIGH", "vectorString": "AV:L/AC:H/PR:N/UI:R/S:U/C:N/I:H/A:H", "confidentialityImpact": "NONE"}, "clustering_coefficient": 0.6666666666666666, "node_degree": [1, 2, 3], "faulty": true, "macke_vulnerabilities_found": 1, "node_path_length": 1.0}, "type": 20.0}, {"id": "{close_tmpoutbuf}", "data": {"macke_bug_chain_length": 0, "distance_to_interface": 1, "clustering_coefficient": 0.3333333333333333, "node_degree": [1, 2, 3], "faulty": false, "macke_vulnerabilities_found": 0, "node_path_length": 1.0}, "type": 0.0}, {"id": "{sem_init}", "data": {"macke_bug_chain_length": 0, "distance_to_interface": 1, "clustering_coefficient": 0.0, "node_degree": [1, 2, 3], "faulty": false, "macke_vulnerabilities_found": 0, "node_path_length": 1.0}, "type": 0.0}, {"id": "{calloc}", "data": {"macke_bug_chain_length": 0, "distance_to_interface": 1, "clustering_coefficient": 0.19047619047619047, "node_degree": [1, 6, 7], "faulty": false, "macke_vulnerabilities_found": 0, "node_path_length": 1.0}, "type": 0.0}, {"id": "{detach_pthread}", "data": {"macke_bug_chain_length": 1, "distance_to_interface": 1, "cvss3": {"scope": "UNCHANGED", "predicted": true, "attackVector": "LOCAL", "privilegesRequired": "NONE", "availabilityImpact": "HIGH", "baseSeverity": "Medium", "baseScore": 6.2, "userInteraction": "NONE", "attackComplexity": "LOW", "integrityImpact": "NONE", "vectorString": "AV:L/AC:L/PR:N/UI:N/S:U/C:N/I:N/A:H", "confidentialityImpact": "NONE"}, "clustering_coefficient": 0.16666666666666666, "node_degree": [2, 2, 4], "faulty": true, "macke_vulnerabilities_found": 1, "node_path_length": 1.5}, "type": 0.6666666666666666}, {"id": "{prepare_streamout_threads}", "data": {"macke_bug_chain_length": 1, "distance_to_interface": 1, "cvss3": {"scope": "UNCHANGED", "predicted": true, "attackVector": "NETWORK", "privilegesRequired": "NONE", "availabilityImpact": "HIGH", "baseSeverity": "High", "baseScore": 7.5, "userInteraction": "NONE", "attackComplexity": "LOW", "integrityImpact": "NONE", "vectorString": "AV:N/AC:L/PR:N/UI:N/S:U/C:N/I:N/A:H", "confidentialityImpact": "NONE"}, "clustering_coefficient": 0.26666666666666666, "node_degree": [5, 1, 6], "faulty": true, "macke_vulnerabilities_found": 1, "node_path_length": 1.4482758620689655}, "type": 1.6}, {"id": "{fatal_exit}", "data": {"macke_bug_chain_length": 0, "distance_to_interface": 1, "clustering_coefficient": 0.3333333333333333, "node_degree": [1, 3, 4], "faulty": false, "macke_vulnerabilities_found": 0, "node_path_length": 1.0}, "type": 0.0}, {"id": "{lrz_crypt}", "data": {"macke_bug_chain_length": 0, "distance_to_interface": 1, "clustering_coefficient": 0.0, "node_degree": [1, 3, 4], "faulty": false, "macke_vulnerabilities_found": 0, "node_path_length": 1.0}, "type": 0.0}, {"id": "Node0x214ff80", "data": {"macke_bug_chain_length": 0, "distance_to_interface": 2, "clustering_coefficient": 0.007058823529411765, "node_degree": [0, 51, 51], "faulty": false, "macke_vulnerabilities_found": 0, "node_path_length": 0}, "type": 0.0}, {"id": "{sem_wait}", "data": {"macke_bug_chain_length": 0, "distance_to_interface": 1, "clustering_coefficient": 0.0, "node_degree": [1, 2, 3], "faulty": false, "macke_vulnerabilities_found": 0, "node_path_length": 1.0}, "type": 0.0}, {"id": "{bzip2_decompress_buf}", "data": {"macke_bug_chain_length": 1, "distance_to_interface": 2, "cvss3": {"scope": "UNCHANGED", "predicted": true, "attackVector": "LOCAL", "privilegesRequired": "NONE", "availabilityImpact": "HIGH", "baseSeverity": "Medium", "baseScore": 5.5, "userInteraction": "REQUIRED", "attackComplexity": "LOW", "integrityImpact": "NONE", "vectorString": "AV:L/AC:L/PR:N/UI:R/S:U/C:N/I:N/A:H", "confidentialityImpact": "NONE"}, "clustering_coefficient": 0.13333333333333333, "node_degree": [5, 1, 6], "faulty": true, "macke_vulnerabilities_found": 1, "node_path_length": 1.0}, "type": 1.6}, {"id": "{pthread_cond_broadcast}", "data": {"macke_bug_chain_length": 0, "distance_to_interface": 1, "clustering_coefficient": 0.0, "node_degree": [1, 2, 3], "faulty": false, "macke_vulnerabilities_found": 0, "node_path_length": 1.0}, "type": 0.0}, {"id": "{open_stream_out}", "data": {"macke_bug_chain_length": 1, "distance_to_interface": 1, "cvss3": {"scope": "UNCHANGED", "predicted": true, "attackVector": "LOCAL", "privilegesRequired": "NONE", "availabilityImpact": "HIGH", "baseSeverity": "Medium", "baseScore": 6.2, "userInteraction": "NONE", "attackComplexity": "LOW", "integrityImpact": "NONE", "vectorString": "AV:L/AC:L/PR:N/UI:N/S:U/C:N/I:N/A:H", "confidentialityImpact": "NONE"}, "clustering_coefficient": 0.2, "node_degree": [5, 1, 6], "faulty": true, "macke_vulnerabilities_found": 1, "node_path_length": 1.0}, "type": 1.2000000000000002}, {"id": "{llvm.memcpy.p0i8.p0i8.i64}", "data": {"macke_bug_chain_length": 0, "distance_to_interface": 1, "clustering_coefficient": 0, "node_degree": [0, 1, 1], "faulty": false, "macke_vulnerabilities_found": 0, "node_path_length": 0}, "type": 0}, {"id": "{dump_stdin}", "data": {"macke_bug_chain_length": 1, "distance_to_interface": 4, "cvss3": {"scope": "UNCHANGED", "predicted": true, "attackVector": "NETWORK", "privilegesRequired": "NONE", "availabilityImpact": "HIGH", "baseSeverity": "High", "baseScore": 7.5, "userInteraction": "NONE", "attackComplexity": "LOW", "integrityImpact": "NONE", "vectorString": "AV:N/AC:L/PR:N/UI:N/S:U/C:N/I:N/A:H", "confidentialityImpact": "NONE"}, "clustering_coefficient": 0.0, "node_degree": [3, 2, 5], "faulty": true, "macke_vulnerabilities_found": 1, "node_path_length": 2.0}, "type": 0.0}, {"id": "{uncompress}", "data": {"macke_bug_chain_length": 0, "distance_to_interface": 1, "clustering_coefficient": 0.0, "node_degree": [1, 2, 3], "faulty": false, "macke_vulnerabilities_found": 0, "node_path_length": 1.0}, "type": 0.0}, {"id": "{gzip_compress_buf}", "data": {"macke_bug_chain_length": 1, "distance_to_interface": 2, "cvss3": {"scope": "UNCHANGED", "predicted": true, "attackVector": "LOCAL", "privilegesRequired": "NONE", "availabilityImpact": "HIGH", "baseSeverity": "Medium", "baseScore": 5.5, "userInteraction": "REQUIRED", "attackComplexity": "LOW", "integrityImpact": "NONE", "vectorString": "AV:L/AC:L/PR:N/UI:R/S:U/C:N/I:N/A:H", "confidentialityImpact": "NONE"}, "clustering_coefficient": 0.14285714285714285, "node_degree": [6, 1, 7], "faulty": true, "macke_vulnerabilities_found": 1, "node_path_length": 1.0}, "type": 2.0}, {"id": "{print_err}", "data": {"macke_bug_chain_length": 9, "distance_to_interface": 2, "cvss3": {"scope": "UNCHANGED", "predicted": true, "attackVector": "LOCAL", "privilegesRequired": "NONE", "availabilityImpact": "HIGH", "baseSeverity": "High", "baseScore": 7.8, "userInteraction": "REQUIRED", "attackComplexity": "LOW", "integrityImpact": "HIGH", "vectorString": "AV:L/AC:L/PR:N/UI:R/S:U/C:H/I:H/A:H", "confidentialityImpact": "HIGH"}, "clustering_coefficient": 0.07114624505928854, "node_degree": [3, 20, 23], "faulty": true, "macke_vulnerabilities_found": 1, "node_path_length": 0}, "type": 29.454545454545457}, {"id": "{close_streamout_threads}", "data": {"macke_bug_chain_length": 1, "distance_to_interface": 1, "cvss3": {"scope": "UNCHANGED", "predicted": true, "attackVector": "NETWORK", "privilegesRequired": "NONE", "availabilityImpact": "HIGH", "baseSeverity": "Critical", "baseScore": 9.8, "userInteraction": "NONE", "attackComplexity": "LOW", "integrityImpact": "HIGH", "vectorString": "AV:N/AC:L/PR:N/UI:N/S:U/C:H/I:H/A:H", "confidentialityImpact": "HIGH"}, "clustering_coefficient": 0.3333333333333333, "node_degree": [2, 1, 3], "faulty": true, "macke_vulnerabilities_found": 1, "node_path_length": 1.0}, "type": 1.0}, {"id": "{get_readseek}", "data": {"macke_bug_chain_length": 1, "distance_to_interface": 1, "cvss3": {"scope": "UNCHANGED", "predicted": true, "attackVector": "NETWORK", "privilegesRequired": "NONE", "availabilityImpact": "HIGH", "baseSeverity": "Critical", "baseScore": 9.1, "userInteraction": "NONE", "attackComplexity": "LOW", "integrityImpact": "NONE", "vectorString": "AV:N/AC:L/PR:N/UI:N/S:U/C:H/I:N/A:H", "confidentialityImpact": "HIGH"}, "clustering_coefficient": 0.3333333333333333, "node_degree": [2, 4, 6], "faulty": true, "macke_vulnerabilities_found": 1, "node_path_length": 1.0}, "type": 2.0}, {"id": "{fsync}", "data": {"macke_bug_chain_length": 0, "distance_to_interface": 1, "clustering_coefficient": 0.16666666666666666, "node_degree": [1, 3, 4], "faulty": false, "macke_vulnerabilities_found": 0, "node_path_length": 1.0}, "type": 0.0}, {"id": "{llvm.va_end}", "data": {"macke_bug_chain_length": 0, "distance_to_interface": 1, "clustering_coefficient": 0, "node_degree": [0, 1, 1], "faulty": false, "macke_vulnerabilities_found": 0, "node_path_length": 0}, "type": 0}, {"id": "{put_fdout}", "data": {"macke_bug_chain_length": 1, "distance_to_interface": 1, "cvss3": {"scope": "UNCHANGED", "predicted": true, "attackVector": "LOCAL", "privilegesRequired": "NONE", "availabilityImpact": "HIGH", "baseSeverity": "High", "baseScore": 7.1, "userInteraction": "REQUIRED", "attackComplexity": "LOW", "integrityImpact": "NONE", "vectorString": "AV:L/AC:L/PR:N/UI:R/S:U/C:H/I:N/A:H", "confidentialityImpact": "HIGH"}, "clustering_coefficient": 0.14285714285714285, "node_degree": [6, 2, 8], "faulty": true, "macke_vulnerabilities_found": 1, "node_path_length": 1.1578947368421053}, "type": 1.1428571428571428}, {"id": "{external node}", "data": {"macke_bug_chain_length": 0, "distance_to_interface": 0, "clustering_coefficient": 0.014439096630877453, "node_degree": [74, 0, 74], "faulty": false, "macke_vulnerabilities_found": 0, "node_path_length": 0}, "type": 0.0}, {"id": "{malloc}", "data": {"macke_bug_chain_length": 0, "distance_to_interface": 1, "clustering_coefficient": 0.03676470588235294, "node_degree": [1, 16, 17], "faulty": false, "macke_vulnerabilities_found": 0, "node_path_length": 1.0}, "type": 0.0}, {"id": "{pthread_cond_wait}", "data": {"macke_bug_chain_length": 0, "distance_to_interface": 1, "clustering_coefficient": 0.0, "node_degree": [1, 2, 3], "faulty": false, "macke_vulnerabilities_found": 0, "node_path_length": 1.0}, "type": 0.0}, {"id": "{pthread_mutex_unlock}", "data": {"macke_bug_chain_length": 0, "distance_to_interface": 1, "clustering_coefficient": 0.3333333333333333, "node_degree": [1, 2, 3], "faulty": false, "macke_vulnerabilities_found": 0, "node_path_length": 1.0}, "type": 0.0}, {"id": "{clear_buffer}", "data": {"macke_bug_chain_length": 1, "distance_to_interface": 2, "cvss3": {"scope": "UNCHANGED", "predicted": true, "attackVector": "LOCAL", "privilegesRequired": "NONE", "availabilityImpact": "HIGH", "baseSeverity": "High", "baseScore": 7.8, "userInteraction": "REQUIRED", "attackComplexity": "LOW", "integrityImpact": "HIGH", "vectorString": "AV:L/AC:L/PR:N/UI:R/S:U/C:H/I:H/A:H", "confidentialityImpact": "HIGH"}, "clustering_coefficient": 0.05555555555555555, "node_degree": [7, 2, 9], "faulty": true, "macke_vulnerabilities_found": 1, "node_path_length": 1.5}, "type": 1.0}, {"id": "{lzma_decompress_buf}", "data": {"macke_bug_chain_length": 1, "distance_to_interface": 2, "cvss3": {"scope": "UNCHANGED", "predicted": true, "attackVector": "LOCAL", "privilegesRequired": "NONE", "availabilityImpact": "HIGH", "baseSeverity": "High", "baseScore": 7.1, "userInteraction": "REQUIRED", "attackComplexity": "LOW", "integrityImpact": "HIGH", "vectorString": "AV:L/AC:L/PR:N/UI:R/S:U/C:N/I:H/A:H", "confidentialityImpact": "NONE"}, "clustering_coefficient": 0.13333333333333333, "node_degree": [5, 1, 6], "faulty": true, "macke_vulnerabilities_found": 1, "node_path_length": 1.125}, "type": 1.6}, {"id": "{lzo_decompress_buf}", "data": {"macke_bug_chain_length": 1, "distance_to_interface": 2, "cvss3": {"scope": "UNCHANGED", "predicted": true, "attackVector": "LOCAL", "privilegesRequired": "NONE", "availabilityImpact": "HIGH", "baseSeverity": "High", "baseScore": 7.1, "userInteraction": "REQUIRED", "attackComplexity": "LOW", "integrityImpact": "HIGH", "vectorString": "AV:L/AC:L/PR:N/UI:R/S:U/C:N/I:H/A:H", "confidentialityImpact": "NONE"}, "clustering_coefficient": 0.13333333333333333, "node_degree": [5, 1, 6], "faulty": true, "macke_vulnerabilities_found": 1, "node_path_length": 1.1428571428571428}, "type": 1.6}, {"id": "{read_1g}", "data": {"macke_bug_chain_length": 5, "distance_to_interface": 1, "faulty": true, "clustering_coefficient": 0.13333333333333333, "node_degree": [4, 2, 6], "cvss3": {"scope": "UNCHANGED", "userInteraction": "REQUIRED", "attackVector": "LOCAL", "attackComplexity": "LOW", "privilegesRequired": "NONE", "integrityImpact": "HIGH", "availabilityImpact": "HIGH", "vectorString": "AV:L/AC:L/PR:N/UI:R/S:U/C:H/I:H/A:H", "baseSeverity": "HIGH", "baseScore": 7.8, "confidentialityImpact": "HIGH"}, "macke_vulnerabilities_found": 1, "node_path_length": 2.2028985507246377}, "type": 999}, {"id": "{read}", "data": {"macke_bug_chain_length": 0, "distance_to_interface": 1, "clustering_coefficient": 0.3333333333333333, "node_degree": [1, 2, 3], "faulty": false, "macke_vulnerabilities_found": 0, "node_path_length": 1.0}, "type": 0.0}, {"id": "{unlock_mutex}", "data": {"macke_bug_chain_length": 1, "distance_to_interface": 1, "cvss3": {"scope": "UNCHANGED", "predicted": true, "attackVector": "LOCAL", "privilegesRequired": "NONE", "availabilityImpact": "HIGH", "baseSeverity": "Medium", "baseScore": 6.2, "userInteraction": "NONE", "attackComplexity": "LOW", "integrityImpact": "NONE", "vectorString": "AV:L/AC:L/PR:N/UI:N/S:U/C:N/I:N/A:H", "confidentialityImpact": "NONE"}, "clustering_coefficient": 0.2857142857142857, "node_degree": [2, 5, 7], "faulty": true, "macke_vulnerabilities_found": 1, "node_path_length": 1.5}, "type": 2.0}, {"id": "{gzip_decompress_buf}", "data": {"macke_bug_chain_length": 1, "distance_to_interface": 2, "cvss3": {"scope": "UNCHANGED", "predicted": true, "attackVector": "LOCAL", "privilegesRequired": "NONE", "availabilityImpact": "HIGH", "baseSeverity": "High", "baseScore": 7.1, "userInteraction": "REQUIRED", "attackComplexity": "LOW", "integrityImpact": "HIGH", "vectorString": "AV:L/AC:L/PR:N/UI:R/S:U/C:N/I:H/A:H", "confidentialityImpact": "NONE"}, "clustering_coefficient": 0.13333333333333333, "node_degree": [5, 1, 6], "faulty": true, "macke_vulnerabilities_found": 1, "node_path_length": 1.2727272727272727}, "type": 1.6}, {"id": "{failure}", "data": {"macke_bug_chain_length": 1, "distance_to_interface": 2, "cvss3": {"scope": "UNCHANGED", "predicted": true, "attackVector": "NETWORK", "privilegesRequired": "NONE", "availabilityImpact": "HIGH", "baseSeverity": "High", "baseScore": 8.1, "userInteraction": "REQUIRED", "attackComplexity": "LOW", "integrityImpact": "NONE", "vectorString": "AV:N/AC:L/PR:N/UI:R/S:U/C:H/I:N/A:H", "confidentialityImpact": "HIGH"}, "clustering_coefficient": 0.07272727272727272, "node_degree": [3, 8, 11], "faulty": true, "macke_vulnerabilities_found": 1, "node_path_length": 1.0}, "type": 1.5999999999999999}, {"id": "{open_stream_in}", "data": {"macke_bug_chain_length": 1, "distance_to_interface": 1, "cvss3": {"scope": "UNCHANGED", "predicted": true, "attackVector": "LOCAL", "privilegesRequired": "NONE", "availabilityImpact": "HIGH", "baseSeverity": "High", "baseScore": 7.1, "userInteraction": "REQUIRED", "attackComplexity": "LOW", "integrityImpact": "NONE", "vectorString": "AV:L/AC:L/PR:N/UI:R/S:U/C:H/I:N/A:H", "confidentialityImpact": "HIGH"}, "clustering_coefficient": 0.12121212121212122, "node_degree": [11, 1, 12], "faulty": true, "macke_vulnerabilities_found": 1, "node_path_length": 1.0}, "type": 1.4545454545454546}, {"id": "{get_rand}", "data": {"macke_bug_chain_length": 0, "distance_to_interface": 1, "clustering_coefficient": 0.3333333333333333, "node_degree": [1, 3, 4], "faulty": false, "macke_vulnerabilities_found": 0, "node_path_length": 1.0}, "type": 0.0}, {"id": "{write_u8}", "data": {"macke_bug_chain_length": 1, "distance_to_interface": 2, "cvss3": {"scope": "UNCHANGED", "predicted": true, "attackVector": "NETWORK", "privilegesRequired": "NONE", "availabilityImpact": "HIGH", "baseSeverity": "Critical", "baseScore": 9.8, "userInteraction": "NONE", "attackComplexity": "LOW", "integrityImpact": "HIGH", "vectorString": "AV:N/AC:L/PR:N/UI:N/S:U/C:H/I:H/A:H", "confidentialityImpact": "HIGH"}, "clustering_coefficient": 1.0, "node_degree": [1, 1, 2], "faulty": true, "macke_vulnerabilities_found": 1, "node_path_length": 1.0}, "type": 4.0}, {"id": "{write_fdout}", "data": {"macke_bug_chain_length": 0, "distance_to_interface": 1, "clustering_coefficient": 0.3333333333333333, "node_degree": [1, 2, 3], "faulty": false, "macke_vulnerabilities_found": 0, "node_path_length": 1.0}, "type": 0.0}, {"id": "{cond_broadcast}", "data": {"macke_bug_chain_length": 1, "distance_to_interface": 2, "cvss3": {"scope": "UNCHANGED", "predicted": true, "attackVector": "NETWORK", "privilegesRequired": "NONE", "availabilityImpact": "HIGH", "baseSeverity": "Medium", "baseScore": 6.5, "userInteraction": "REQUIRED", "attackComplexity": "LOW", "integrityImpact": "NONE", "vectorString": "AV:N/AC:L/PR:N/UI:R/S:U/C:N/I:N/A:H", "confidentialityImpact": "NONE"}, "clustering_coefficient": 0.3333333333333333, "node_degree": [2, 2, 4], "faulty": true, "macke_vulnerabilities_found": 1, "node_path_length": 1.3333333333333333}, "type": 2.6666666666666665}, {"id": "{compthread}", "data": {"macke_bug_chain_length": 1, "distance_to_interface": 1, "cvss3": {"scope": "UNCHANGED", "predicted": true, "attackVector": "LOCAL", "privilegesRequired": "NONE", "availabilityImpact": "HIGH", "baseSeverity": "High", "baseScore": 7.8, "userInteraction": "REQUIRED", "attackComplexity": "LOW", "integrityImpact": "HIGH", "vectorString": "AV:L/AC:L/PR:N/UI:R/S:U/C:H/I:H/A:H", "confidentialityImpact": "HIGH"}, "clustering_coefficient": 0.11083743842364532, "node_degree": [28, 1, 29], "faulty": true, "macke_vulnerabilities_found": 1, "node_path_length": 1.8244422890397671}, "type": 3.2142857142857144}, {"id": "{close_tmpinbuf}", "data": {"macke_bug_chain_length": 0, "distance_to_interface": 1, "clustering_coefficient": 0.0, "node_degree": [1, 2, 3], "faulty": false, "macke_vulnerabilities_found": 0, "node_path_length": 1.0}, "type": 0.0}, {"id": "{close_stream_in}", "data": {"macke_bug_chain_length": 1, "distance_to_interface": 1, "cvss3": {"scope": "UNCHANGED", "predicted": true, "attackVector": "LOCAL", "privilegesRequired": "NONE", "availabilityImpact": "HIGH", "baseSeverity": "High", "baseScore": 7.7, "userInteraction": "NONE", "attackComplexity": "LOW", "integrityImpact": "NONE", "vectorString": "AV:L/AC:L/PR:N/UI:N/S:U/C:H/I:N/A:H", "confidentialityImpact": "HIGH"}, "clustering_coefficient": 0.2, "node_degree": [4, 1, 5], "faulty": true, "macke_vulnerabilities_found": 1, "node_path_length": 1.0}, "type": 1.0}, {"id": "{llvm.expect.i64}", "data": {"macke_bug_chain_length": 0, "distance_to_interface": 1, "clustering_coefficient": 0, "node_degree": [0, 1, 1], "faulty": false, "macke_vulnerabilities_found": 0, "node_path_length": 0}, "type": 0}, {"id": "{perror}", "data": {"macke_bug_chain_length": 0, "distance_to_interface": 1, "clustering_coefficient": 0.3333333333333333, "node_degree": [1, 2, 3], "faulty": false, "macke_vulnerabilities_found": 0, "node_path_length": 1.0}, "type": 0.0}, {"id": "{rewrite_encrypted}", "data": {"macke_bug_chain_length": 1, "distance_to_interface": 2, "cvss3": {"scope": "UNCHANGED", "predicted": true, "attackVector": "LOCAL", "privilegesRequired": "NONE", "availabilityImpact": "HIGH", "baseSeverity": "High", "baseScore": 7.1, "userInteraction": "REQUIRED", "attackComplexity": "LOW", "integrityImpact": "HIGH", "vectorString": "AV:L/AC:L/PR:N/UI:R/S:U/C:N/I:H/A:H", "confidentialityImpact": "NONE"}, "clustering_coefficient": 0.13636363636363635, "node_degree": [10, 2, 12], "faulty": true, "macke_vulnerabilities_found": 1, "node_path_length": 1.5658536585365854}, "type": 3.2727272727272725}, {"id": "{read_seekto}", "data": {"macke_bug_chain_length": 5, "distance_to_interface": 2, "cvss3": {"scope": "UNCHANGED", "predicted": true, "attackVector": "LOCAL", "privilegesRequired": "NONE", "availabilityImpact": "HIGH", "baseSeverity": "High", "baseScore": 7.1, "userInteraction": "REQUIRED", "attackComplexity": "LOW", "integrityImpact": "HIGH", "vectorString": "AV:L/AC:L/PR:N/UI:R/S:U/C:N/I:H/A:H", "confidentialityImpact": "NONE"}, "clustering_coefficient": 0.06666666666666667, "node_degree": [4, 2, 6], "faulty": true, "macke_vulnerabilities_found": 1, "node_path_length": 1.4}, "type": 4.0}], "links": [{"target": "Node0x214ff80", "source": "{vfprintf}"}, {"target": "Node0x214ff80", "source": "{zpaq_compress}"}, {"target": "{print_err}", "source": "{read_buf}"}, {"target": "{print_err}", "source": "{read_buf}"}, {"target": "{strerror}", "source": "{read_buf}"}, {"target": "{__errno_location}", "source": "{read_buf}"}, {"target": "{read_1g}", "source": "{read_buf}"}, {"target": "{free}", "source": "{bzip2_compress_buf}"}, {"target": "{free}", "source": "{bzip2_compress_buf}"}, {"target": "{free}", "source": "{bzip2_compress_buf}"}, {"target": "{free}", "source": "{bzip2_compress_buf}"}, {"target": "{print_stuff}", "source": "{bzip2_compress_buf}"}, {"target": "{print_stuff}", "source": "{bzip2_compress_buf}"}, {"target": "{print_stuff}", "source": "{bzip2_compress_buf}"}, {"target": "{BZ2_bzBuffToBuffCompress}", "source": "{bzip2_compress_buf}"}, {"target": "{print_err}", "source": "{bzip2_compress_buf}"}, {"target": "{malloc}", "source": "{bzip2_compress_buf}"}, {"target": "{lzo_compresses}", "source": "{bzip2_compress_buf}"}, {"target": "{round_up_page}", "source": "{bzip2_compress_buf}"}, {"target": "{sem_init}", "source": "{cksem_init}"}, {"target": "{fatal}", "source": "{cksem_init}"}, {"target": "{__errno_location}", "source": "{cksem_init}"}, {"target": "Node0x214ff80", "source": "{__errno_location}"}, {"target": "Node0x214ff80", "source": "{getchar}"}, {"target": "{vfprintf}", "source": "{print_stuff}"}, {"target": "Node0x214ff80", "source": "{print_stuff}"}, {"target": "{fflush}", "source": "{print_stuff}"}, {"target": "{failure}", "source": "{fill_buffer}"}, {"target": "{read_val}", "source": "{fill_buffer}"}, {"target": "{read_val}", "source": "{fill_buffer}"}, {"target": "{read_val}", "source": "{fill_buffer}"}, {"target": "{lrz_decrypt}", "source": "{fill_buffer}"}, {"target": "{read_seekto}", "source": "{fill_buffer}"}, {"target": "{cond_broadcast}", "source": "{fill_buffer}"}, {"target": "{join_pthread}", "source": "{fill_buffer}"}, {"target": "{read_buf}", "source": "{fill_buffer}"}, {"target": "{read_buf}", "source": "{fill_buffer}"}, {"target": "{read_buf}", "source": "{fill_buffer}"}, {"target": "{malloc}", "source": "{fill_buffer}"}, {"target": "{malloc}", "source": "{fill_buffer}"}, {"target": "{read_u32}", "source": "{fill_buffer}"}, {"target": "{read_u32}", "source": "{fill_buffer}"}, {"target": "{read_u32}", "source": "{fill_buffer}"}, {"target": "{create_pthread}", "source": "{fill_buffer}"}, {"target": "{free}", "source": "{fill_buffer}"}, {"target": "{free}", "source": "{fill_buffer}"}, {"target": "{fatal}", "source": "{fill_buffer}"}, {"target": "{fatal}", "source": "{fill_buffer}"}, {"target": "{fatal}", "source": "{fill_buffer}"}, {"target": "{print_stuff}", "source": "{fill_buffer}"}, {"target": "{print_stuff}", "source": "{fill_buffer}"}, {"target": "{print_stuff}", "source": "{fill_buffer}"}, {"target": "{print_stuff}", "source": "{fill_buffer}"}, {"target": "{read_u8}", "source": "{fill_buffer}"}, {"target": "{decrypt_header}", "source": "{fill_buffer}"}, {"target": "{lock_mutex}", "source": "{fill_buffer}"}, {"target": "{unlock_mutex}", "source": "{fill_buffer}"}, {"target": "{get_readseek}", "source": "{fill_buffer}"}, {"target": "{fsync}", "source": "{fill_buffer}"}, {"target": "Node0x214ff80", "source": "{pthread_detach}"}, {"target": "{pthread_mutex_lock}", "source": "{lock_mutex}"}, {"target": "{fatal}", "source": "{lock_mutex}"}, {"target": "{fill_buffer}", "source": "{read_stream}"}, {"target": "{fatal}", "source": "{cksem_post}"}, {"target": "{sem_post}", "source": "{cksem_post}"}, {"target": "{__errno_location}", "source": "{cksem_post}"}, {"target": "{gzip_decompress_buf}", "source": "{ucompthread}"}, {"target": "{zpaq_decompress_buf}", "source": "{ucompthread}"}, {"target": "{failure}", "source": "{ucompthread}"}, {"target": "{failure}", "source": "{ucompthread}"}, {"target": "{bzip2_decompress_buf}", "source": "{ucompthread}"}, {"target": "{setpriority}", "source": "{ucompthread}"}, {"target": "{cond_wait}", "source": "{ucompthread}"}, {"target": "{lzma_decompress_buf}", "source": "{ucompthread}"}, {"target": "{free}", "source": "{ucompthread}"}, {"target": "{lzo_decompress_buf}", "source": "{ucompthread}"}, {"target": "{print_stuff}", "source": "{ucompthread}"}, {"target": "{print_stuff}", "source": "{ucompthread}"}, {"target": "{print_err}", "source": "{ucompthread}"}, {"target": "{lock_mutex}", "source": "{ucompthread}"}, {"target": "{unlock_mutex}", "source": "{ucompthread}"}, {"target": "{write_buf}", "source": "{write_val}"}, {"target": "{free}", "source": "{lzo_compresses}"}, {"target": "{free}", "source": "{lzo_compresses}"}, {"target": "{free}", "source": "{lzo_compresses}"}, {"target": "{fatal}", "source": "{lzo_compresses}"}, {"target": "{fatal}", "source": "{lzo_compresses}"}, {"target": "{print_stuff}", "source": "{lzo_compresses}"}, {"target": "{malloc}", "source": "{lzo_compresses}"}, {"target": "{malloc}", "source": "{lzo_compresses}"}, {"target": "{lzo1x_1_compress}", "source": "{lzo_compresses}"}, {"target": "Node0x214ff80", "source": "{compress2}"}, {"target": "Node0x214ff80", "source": "{free}"}, {"target": "Node0x214ff80", "source": "{write}"}, {"target": "{pthread_create}", "source": "{create_pthread}"}, {"target": "{fatal}", "source": "{create_pthread}"}, {"target": "{clear_buffer}", "source": "{flush_buffer}"}, {"target": "{read_buf}", "source": "{read_u8}"}, {"target": "Node0x214ff80", "source": "{pthread_mutex_lock}"}, {"target": "{print_err}", "source": "{zpaq_compress_buf}"}, {"target": "{free}", "source": "{zpaq_compress_buf}"}, {"target": "{free}", "source": "{zpaq_compress_buf}"}, {"target": "{print_stuff}", "source": "{zpaq_compress_buf}"}, {"target": "{zpaq_compress}", "source": "{zpaq_compress_buf}"}, {"target": "{malloc}", "source": "{zpaq_compress_buf}"}, {"target": "{lzo_compresses}", "source": "{zpaq_compress_buf}"}, {"target": "{round_up_page}", "source": "{zpaq_compress_buf}"}, {"target": "Node0x214ff80", "source": "{sem_post}"}, {"target": "Node0x214ff80", "source": "{read_tmpinfile}"}, {"target": "{read_buf}", "source": "{read_val}"}, {"target": "Node0x214ff80", "source": "{BZ2_bzBuffToBuffCompress}"}, {"target": "{fatal}", "source": "{cksem_wait}"}, {"target": "{sem_wait}", "source": "{cksem_wait}"}, {"target": "{__errno_location}", "source": "{cksem_wait}"}, {"target": "{free}", "source": "{lzma_compress_buf}"}, {"target": "{free}", "source": "{lzma_compress_buf}"}, {"target": "{free}", "source": "{lzma_compress_buf}"}, {"target": "{print_stuff}", "source": "{lzma_compress_buf}"}, {"target": "{print_stuff}", "source": "{lzma_compress_buf}"}, {"target": "{print_stuff}", "source": "{lzma_compress_buf}"}, {"target": "{print_stuff}", "source": "{lzma_compress_buf}"}, {"target": "{print_stuff}", "source": "{lzma_compress_buf}"}, {"target": "{LzmaCompress}", "source": "{lzma_compress_buf}"}, {"target": "{print_err}", "source": "{lzma_compress_buf}"}, {"target": "{print_err}", "source": "{lzma_compress_buf}"}, {"target": "{print_err}", "source": "{lzma_compress_buf}"}, {"target": "{print_err}", "source": "{lzma_compress_buf}"}, {"target": "{bzip2_compress_buf}", "source": "{lzma_compress_buf}"}, {"target": "{malloc}", "source": "{lzma_compress_buf}"}, {"target": "{lock_mutex}", "source": "{lzma_compress_buf}"}, {"target": "{unlock_mutex}", "source": "{lzma_compress_buf}"}, {"target": "{lzo_compresses}", "source": "{lzma_compress_buf}"}, {"target": "{round_up_page}", "source": "{lzma_compress_buf}"}, {"target": "{free}", "source": "{lzo_compress_buf}"}, {"target": "{free}", "source": "{lzo_compress_buf}"}, {"target": "{free}", "source": "{lzo_compress_buf}"}, {"target": "{print_stuff}", "source": "{lzo_compress_buf}"}, {"target": "{print_stuff}", "source": "{lzo_compress_buf}"}, {"target": "{lzo1x_1_compress}", "source": "{lzo_compress_buf}"}, {"target": "{print_err}", "source": "{lzo_compress_buf}"}, {"target": "{calloc}", "source": "{lzo_compress_buf}"}, {"target": "{malloc}", "source": "{lzo_compress_buf}"}, {"target": "{round_up_page}", "source": "{lzo_compress_buf}"}, {"target": "Node0x214ff80", "source": "{pthread_mutex_init}"}, {"target": "{lrz_crypt}", "source": "{lrz_encrypt}"}, {"target": "Node0x214ff80", "source": "{realloc}"}, {"target": "Node0x214ff80", "source": "{zpaq_decompress}"}, {"target": "Node0x214ff80", "source": "{write_magic}"}, {"target": "Node0x214ff80", "source": "{LzmaUncompress}"}, {"target": "Node0x214ff80", "source": "{flush_tmpoutbuf}"}, {"target": "{getchar}", "source": "{read_fdin}"}, {"target": "{failure}", "source": "{read_fdin}"}, {"target": "Node0x214ff80", "source": "{lseek}"}, {"target": "{realloc}", "source": "{close_stream_out}"}, {"target": "{clear_buffer}", "source": "{close_stream_out}"}, {"target": "{cksem_post}", "source": "{close_stream_out}"}, {"target": "{print_err}", "source": "{close_stream_out}"}, {"target": "{print_err}", "source": "{close_stream_out}"}, {"target": "{calloc}", "source": "{close_stream_out}"}, {"target": "{cksem_wait}", "source": "{close_stream_out}"}, {"target": "{rewrite_encrypted}", "source": "{close_stream_out}"}, {"target": "{zpaq_decompress}", "source": "{zpaq_decompress_buf}"}, {"target": "{print_err}", "source": "{zpaq_decompress_buf}"}, {"target": "{print_err}", "source": "{zpaq_decompress_buf}"}, {"target": "{free}", "source": "{zpaq_decompress_buf}"}, {"target": "{malloc}", "source": "{zpaq_decompress_buf}"}, {"target": "{round_up_page}", "source": "{zpaq_decompress_buf}"}, {"target": "{fatal}", "source": "{cond_wait}"}, {"target": "{pthread_cond_wait}", "source": "{cond_wait}"}, {"target": "{vfprintf}", "source": "{fatal}"}, {"target": "Node0x214ff80", "source": "{fatal}"}, {"target": "{fatal_exit}", "source": "{fatal}"}, {"target": "{perror}", "source": "{fatal}"}, {"target": "Node0x214ff80", "source": "{lzo1x_decompress}"}, {"target": "{print_err}", "source": "{write_buf}"}, {"target": "{print_err}", "source": "{write_buf}"}, {"target": "{write_1g}", "source": "{write_buf}"}, {"target": "{strerror}", "source": "{write_buf}"}, {"target": "{__errno_location}", "source": "{write_buf}"}, {"target": "{fatal}", "source": "{init_mutex}"}, {"target": "{pthread_mutex_init}", "source": "{init_mutex}"}, {"target": "Node0x214ff80", "source": "{write_fdin}"}, {"target": "{put_fdout}", "source": "{write_1g}"}, {"target": "Node0x214ff80", "source": "{round_up_page}"}, {"target": "Node0x214ff80", "source": "{LzmaCompress}"}, {"target": "{print_err}", "source": "{fd_seekto}"}, {"target": "{lseek}", "source": "{fd_seekto}"}, {"target": "Node0x214ff80", "source": "{lzo1x_1_compress}"}, {"target": "{print_err}", "source": "{seekto}"}, {"target": "{fd_seekto}", "source": "{seekto}"}, {"target": "{lrz_decrypt}", "source": "{decrypt_header}"}, {"target": "Node0x214ff80", "source": "{strerror}"}, {"target": "{flush_buffer}", "source": "{write_stream}"}, {"target": "{fatal}", "source": "{get_seek}"}, {"target": "{lseek}", "source": "{get_seek}"}, {"target": "Node0x214ff80", "source": "{pthread_join}"}, {"target": "Node0x214ff80", "source": "{fflush}"}, {"target": "Node0x214ff80", "source": "{setpriority}"}, {"target": "{fatal}", "source": "{join_pthread}"}, {"target": "{pthread_join}", "source": "{join_pthread}"}, {"target": "Node0x214ff80", "source": "{BZ2_bzBuffToBuffDecompress}"}, {"target": "{lrz_crypt}", "source": "{lrz_decrypt}"}, {"target": "Node0x214ff80", "source": "{pthread_create}"}, {"target": "{read_buf}", "source": "{read_u32}"}, {"target": "Node0x214ff80", "source": "{close_tmpoutbuf}"}, {"target": "Node0x214ff80", "source": "{sem_init}"}, {"target": "Node0x214ff80", "source": "{calloc}"}, {"target": "{pthread_detach}", "source": "{detach_pthread}"}, {"target": "{fatal}", "source": "{detach_pthread}"}, {"target": "{calloc}", "source": "{prepare_streamout_threads}"}, {"target": "{calloc}", "source": "{prepare_streamout_threads}"}, {"target": "{free}", "source": "{prepare_streamout_threads}"}, {"target": "{fatal}", "source": "{prepare_streamout_threads}"}, {"target": "{fatal}", "source": "{prepare_streamout_threads}"}, {"target": "{cksem_post}", "source": "{prepare_streamout_threads}"}, {"target": "{cksem_init}", "source": "{prepare_streamout_threads}"}, {"target": "Node0x214ff80", "source": "{fatal_exit}"}, {"target": "Node0x214ff80", "source": "{lrz_crypt}"}, {"target": "Node0x214ff80", "source": "{sem_wait}"}, {"target": "{BZ2_bzBuffToBuffDecompress}", "source": "{bzip2_decompress_buf}"}, {"target": "{print_err}", "source": "{bzip2_decompress_buf}"}, {"target": "{print_err}", "source": "{bzip2_decompress_buf}"}, {"target": "{print_err}", "source": "{bzip2_decompress_buf}"}, {"target": "{free}", "source": "{bzip2_decompress_buf}"}, {"target": "{free}", "source": "{bzip2_decompress_buf}"}, {"target": "{malloc}", "source": "{bzip2_decompress_buf}"}, {"target": "{round_up_page}", "source": "{bzip2_decompress_buf}"}, {"target": "Node0x214ff80", "source": "{pthread_cond_broadcast}"}, {"target": "{calloc}", "source": "{open_stream_out}"}, {"target": "{calloc}", "source": "{open_stream_out}"}, {"target": "{calloc}", "source": "{open_stream_out}"}, {"target": "{free}", "source": "{open_stream_out}"}, {"target": "{free}", "source": "{open_stream_out}"}, {"target": "{free}", "source": "{open_stream_out}"}, {"target": "{free}", "source": "{open_stream_out}"}, {"target": "{free}", "source": "{open_stream_out}"}, {"target": "{free}", "source": "{open_stream_out}"}, {"target": "{fatal}", "source": "{open_stream_out}"}, {"target": "{malloc}", "source": "{open_stream_out}"}, {"target": "{malloc}", "source": "{open_stream_out}"}, {"target": "{print_stuff}", "source": "{open_stream_out}"}, {"target": "{print_stuff}", "source": "{open_stream_out}"}, {"target": "{print_stuff}", "source": "{open_stream_out}"}, {"target": "{write_fdin}", "source": "{dump_stdin}"}, {"target": "{close_tmpinbuf}", "source": "{dump_stdin}"}, {"target": "{read_tmpinfile}", "source": "{dump_stdin}"}, {"target": "Node0x214ff80", "source": "{uncompress}"}, {"target": "{free}", "source": "{gzip_compress_buf}"}, {"target": "{free}", "source": "{gzip_compress_buf}"}, {"target": "{free}", "source": "{gzip_compress_buf}"}, {"target": "{free}", "source": "{gzip_compress_buf}"}, {"target": "{print_stuff}", "source": "{gzip_compress_buf}"}, {"target": "{print_stuff}", "source": "{gzip_compress_buf}"}, {"target": "{print_stuff}", "source": "{gzip_compress_buf}"}, {"target": "{print_err}", "source": "{gzip_compress_buf}"}, {"target": "{malloc}", "source": "{gzip_compress_buf}"}, {"target": "{compress2}", "source": "{gzip_compress_buf}"}, {"target": "{round_up_page}", "source": "{gzip_compress_buf}"}, {"target": "{vfprintf}", "source": "{print_err}"}, {"target": "Node0x214ff80", "source": "{print_err}"}, {"target": "{fflush}", "source": "{print_err}"}, {"target": "{cksem_wait}", "source": "{close_streamout_threads}"}, {"target": "{free}", "source": "{close_streamout_threads}"}, {"target": "{free}", "source": "{close_streamout_threads}"}, {"target": "{fatal}", "source": "{get_readseek}"}, {"target": "{lseek}", "source": "{get_readseek}"}, {"target": "Node0x214ff80", "source": "{fsync}"}, {"target": "{failure}", "source": "{put_fdout}"}, {"target": "{print_stuff}", "source": "{put_fdout}"}, {"target": "{close_tmpoutbuf}", "source": "{put_fdout}"}, {"target": "{print_err}", "source": "{put_fdout}"}, {"target": "{print_err}", "source": "{put_fdout}"}, {"target": "{write_fdout}", "source": "{put_fdout}"}, {"target": "{write_fdout}", "source": "{put_fdout}"}, {"target": "{write}", "source": "{put_fdout}"}, {"target": "{lzo1x_1_compress}", "source": "{external node}"}, {"target": "{pthread_join}", "source": "{external node}"}, {"target": "{close_tmpoutbuf}", "source": "{external node}"}, {"target": "{pthread_create}", "source": "{external node}"}, {"target": "{setpriority}", "source": "{external node}"}, {"target": "{join_pthread}", "source": "{external node}"}, {"target": "{__errno_location}", "source": "{external node}"}, {"target": "{BZ2_bzBuffToBuffDecompress}", "source": "{external node}"}, {"target": "{free}", "source": "{external node}"}, {"target": "{llvm.memset.p0i8.i64}", "source": "{external node}"}, {"target": "{read_stream}", "source": "{external node}"}, {"target": "{sem_init}", "source": "{external node}"}, {"target": "{calloc}", "source": "{external node}"}, {"target": "{detach_pthread}", "source": "{external node}"}, {"target": "{prepare_streamout_threads}", "source": "{external node}"}, {"target": "{lock_mutex}", "source": "{external node}"}, {"target": "{pthread_detach}", "source": "{external node}"}, {"target": "{fatal_exit}", "source": "{external node}"}, {"target": "{lrz_crypt}", "source": "{external node}"}, {"target": "{zpaq_compress}", "source": "{external node}"}, {"target": "{ucompthread}", "source": "{external node}"}, {"target": "{create_pthread}", "source": "{external node}"}, {"target": "{write_fdin}", "source": "{external node}"}, {"target": "{BZ2_bzBuffToBuffCompress}", "source": "{external node}"}, {"target": "{open_stream_out}", "source": "{external node}"}, {"target": "{compress2}", "source": "{external node}"}, {"target": "{llvm.memcpy.p0i8.p0i8.i64}", "source": "{external node}"}, {"target": "{unlock_mutex}", "source": "{external node}"}, {"target": "{open_stream_in}", "source": "{external node}"}, {"target": "{fflush}", "source": "{external node}"}, {"target": "{flush_buffer}", "source": "{external node}"}, {"target": "{close_streamout_threads}", "source": "{external node}"}, {"target": "{getchar}", "source": "{external node}"}, {"target": "{sem_post}", "source": "{external node}"}, {"target": "{read_tmpinfile}", "source": "{external node}"}, {"target": "{get_readseek}", "source": "{external node}"}, {"target": "{fsync}", "source": "{external node}"}, {"target": "{flush_tmpoutbuf}", "source": "{external node}"}, {"target": "{llvm.va_end}", "source": "{external node}"}, {"target": "{perror}", "source": "{external node}"}, {"target": "{put_fdout}", "source": "{external node}"}, {"target": "{uncompress}", "source": "{external node}"}, {"target": "{pthread_cond_broadcast}", "source": "{external node}"}, {"target": "{malloc}", "source": "{external node}"}, {"target": "{pthread_cond_wait}", "source": "{external node}"}, {"target": "{pthread_mutex_init}", "source": "{external node}"}, {"target": "{read}", "source": "{external node}"}, {"target": "{pthread_mutex_unlock}", "source": "{external node}"}, {"target": "{zpaq_decompress}", "source": "{external node}"}, {"target": "{LzmaUncompress}", "source": "{external node}"}, {"target": "{read_1g}", "source": "{external node}"}, {"target": "{pthread_mutex_lock}", "source": "{external node}"}, {"target": "{lseek}", "source": "{external node}"}, {"target": "{close_stream_out}", "source": "{external node}"}, {"target": "{write}", "source": "{external node}"}, {"target": "{realloc}", "source": "{external node}"}, {"target": "{vfprintf}", "source": "{external node}"}, {"target": "{write_magic}", "source": "{external node}"}, {"target": "{lzo1x_decompress}", "source": "{external node}"}, {"target": "{sem_wait}", "source": "{external node}"}, {"target": "{get_rand}", "source": "{external node}"}, {"target": "{strerror}", "source": "{external node}"}, {"target": "{write_fdout}", "source": "{external node}"}, {"target": "{write_1g}", "source": "{external node}"}, {"target": "{llvm.dbg.declare}", "source": "{external node}"}, {"target": "{round_up_page}", "source": "{external node}"}, {"target": "{LzmaCompress}", "source": "{external node}"}, {"target": "{compthread}", "source": "{external node}"}, {"target": "{close_tmpinbuf}", "source": "{external node}"}, {"target": "{init_mutex}", "source": "{external node}"}, {"target": "{close_stream_in}", "source": "{external node}"}, {"target": "{llvm.expect.i64}", "source": "{external node}"}, {"target": "{llvm.va_start}", "source": "{external node}"}, {"target": "{write_stream}", "source": "{external node}"}, {"target": "Node0x214ff80", "source": "{malloc}"}, {"target": "Node0x214ff80", "source": "{pthread_cond_wait}"}, {"target": "Node0x214ff80", "source": "{pthread_mutex_unlock}"}, {"target": "{cksem_wait}", "source": "{clear_buffer}"}, {"target": "{cksem_post}", "source": "{clear_buffer}"}, {"target": "{failure}", "source": "{clear_buffer}"}, {"target": "{failure}", "source": "{clear_buffer}"}, {"target": "{failure}", "source": "{clear_buffer}"}, {"target": "{print_stuff}", "source": "{clear_buffer}"}, {"target": "{create_pthread}", "source": "{clear_buffer}"}, {"target": "{detach_pthread}", "source": "{clear_buffer}"}, {"target": "{malloc}", "source": "{clear_buffer}"}, {"target": "{malloc}", "source": "{clear_buffer}"}, {"target": "{print_err}", "source": "{lzma_decompress_buf}"}, {"target": "{print_err}", "source": "{lzma_decompress_buf}"}, {"target": "{print_err}", "source": "{lzma_decompress_buf}"}, {"target": "{free}", "source": "{lzma_decompress_buf}"}, {"target": "{free}", "source": "{lzma_decompress_buf}"}, {"target": "{malloc}", "source": "{lzma_decompress_buf}"}, {"target": "{LzmaUncompress}", "source": "{lzma_decompress_buf}"}, {"target": "{round_up_page}", "source": "{lzma_decompress_buf}"}, {"target": "{print_err}", "source": "{lzo_decompress_buf}"}, {"target": "{print_err}", "source": "{lzo_decompress_buf}"}, {"target": "{print_err}", "source": "{lzo_decompress_buf}"}, {"target": "{free}", "source": "{lzo_decompress_buf}"}, {"target": "{free}", "source": "{lzo_decompress_buf}"}, {"target": "{lzo1x_decompress}", "source": "{lzo_decompress_buf}"}, {"target": "{malloc}", "source": "{lzo_decompress_buf}"}, {"target": "{round_up_page}", "source": "{lzo_decompress_buf}"}, {"target": "{read_fdin}", "source": "{read_1g}"}, {"target": "{failure}", "source": "{read_1g}"}, {"target": "{failure}", "source": "{read_1g}"}, {"target": "{dump_stdin}", "source": "{read_1g}"}, {"target": "{read}", "source": "{read_1g}"}, {"target": "Node0x214ff80", "source": "{read}"}, {"target": "{pthread_mutex_unlock}", "source": "{unlock_mutex}"}, {"target": "{fatal}", "source": "{unlock_mutex}"}, {"target": "{print_err}", "source": "{gzip_decompress_buf}"}, {"target": "{print_err}", "source": "{gzip_decompress_buf}"}, {"target": "{print_err}", "source": "{gzip_decompress_buf}"}, {"target": "{uncompress}", "source": "{gzip_decompress_buf}"}, {"target": "{free}", "source": "{gzip_decompress_buf}"}, {"target": "{free}", "source": "{gzip_decompress_buf}"}, {"target": "{malloc}", "source": "{gzip_decompress_buf}"}, {"target": "{round_up_page}", "source": "{gzip_decompress_buf}"}, {"target": "{vfprintf}", "source": "{failure}"}, {"target": "Node0x214ff80", "source": "{failure}"}, {"target": "{fatal_exit}", "source": "{failure}"}, {"target": "{read_u8}", "source": "{open_stream_in}"}, {"target": "{read_u8}", "source": "{open_stream_in}"}, {"target": "{free}", "source": "{open_stream_in}"}, {"target": "{free}", "source": "{open_stream_in}"}, {"target": "{free}", "source": "{open_stream_in}"}, {"target": "{free}", "source": "{open_stream_in}"}, {"target": "{free}", "source": "{open_stream_in}"}, {"target": "{fatal}", "source": "{open_stream_in}"}, {"target": "{read_val}", "source": "{open_stream_in}"}, {"target": "{read_val}", "source": "{open_stream_in}"}, {"target": "{read_val}", "source": "{open_stream_in}"}, {"target": "{read_val}", "source": "{open_stream_in}"}, {"target": "{print_stuff}", "source": "{open_stream_in}"}, {"target": "{print_stuff}", "source": "{open_stream_in}"}, {"target": "{print_stuff}", "source": "{open_stream_in}"}, {"target": "{print_stuff}", "source": "{open_stream_in}"}, {"target": "{print_stuff}", "source": "{open_stream_in}"}, {"target": "{read_buf}", "source": "{open_stream_in}"}, {"target": "{print_err}", "source": "{open_stream_in}"}, {"target": "{print_err}", "source": "{open_stream_in}"}, {"target": "{print_err}", "source": "{open_stream_in}"}, {"target": "{print_err}", "source": "{open_stream_in}"}, {"target": "{print_err}", "source": "{open_stream_in}"}, {"target": "{print_err}", "source": "{open_stream_in}"}, {"target": "{print_err}", "source": "{open_stream_in}"}, {"target": "{calloc}", "source": "{open_stream_in}"}, {"target": "{calloc}", "source": "{open_stream_in}"}, {"target": "{calloc}", "source": "{open_stream_in}"}, {"target": "{calloc}", "source": "{open_stream_in}"}, {"target": "{read_u32}", "source": "{open_stream_in}"}, {"target": "{read_u32}", "source": "{open_stream_in}"}, {"target": "{read_u32}", "source": "{open_stream_in}"}, {"target": "{decrypt_header}", "source": "{open_stream_in}"}, {"target": "{get_readseek}", "source": "{open_stream_in}"}, {"target": "{get_readseek}", "source": "{open_stream_in}"}, {"target": "{get_readseek}", "source": "{open_stream_in}"}, {"target": "{get_readseek}", "source": "{open_stream_in}"}, {"target": "Node0x214ff80", "source": "{get_rand}"}, {"target": "{write_buf}", "source": "{write_u8}"}, {"target": "Node0x214ff80", "source": "{write_fdout}"}, {"target": "{fatal}", "source": "{cond_broadcast}"}, {"target": "{pthread_cond_broadcast}", "source": "{cond_broadcast}"}, {"target": "{get_seek}", "source": "{compthread}"}, {"target": "{get_seek}", "source": "{compthread}"}, {"target": "{cond_wait}", "source": "{compthread}"}, {"target": "{bzip2_compress_buf}", "source": "{compthread}"}, {"target": "{lzo_compress_buf}", "source": "{compthread}"}, {"target": "{lrz_encrypt}", "source": "{compthread}"}, {"target": "{realloc}", "source": "{compthread}"}, {"target": "{seekto}", "source": "{compthread}"}, {"target": "{seekto}", "source": "{compthread}"}, {"target": "{free}", "source": "{compthread}"}, {"target": "{free}", "source": "{compthread}"}, {"target": "{cksem_post}", "source": "{compthread}"}, {"target": "{print_stuff}", "source": "{compthread}"}, {"target": "{print_stuff}", "source": "{compthread}"}, {"target": "{print_stuff}", "source": "{compthread}"}, {"target": "{print_stuff}", "source": "{compthread}"}, {"target": "{print_stuff}", "source": "{compthread}"}, {"target": "{print_stuff}", "source": "{compthread}"}, {"target": "{print_stuff}", "source": "{compthread}"}, {"target": "{print_stuff}", "source": "{compthread}"}, {"target": "{gzip_compress_buf}", "source": "{compthread}"}, {"target": "{lock_mutex}", "source": "{compthread}"}, {"target": "{lock_mutex}", "source": "{compthread}"}, {"target": "{lock_mutex}", "source": "{compthread}"}, {"target": "{unlock_mutex}", "source": "{compthread}"}, {"target": "{unlock_mutex}", "source": "{compthread}"}, {"target": "{unlock_mutex}", "source": "{compthread}"}, {"target": "{write_magic}", "source": "{compthread}"}, {"target": "{write_buf}", "source": "{compthread}"}, {"target": "{write_buf}", "source": "{compthread}"}, {"target": "{get_rand}", "source": "{compthread}"}, {"target": "{get_rand}", "source": "{compthread}"}, {"target": "{write_u8}", "source": "{compthread}"}, {"target": "{write_u8}", "source": "{compthread}"}, {"target": "{write_u8}", "source": "{compthread}"}, {"target": "{write_u8}", "source": "{compthread}"}, {"target": "{write_val}", "source": "{compthread}"}, {"target": "{write_val}", "source": "{compthread}"}, {"target": "{write_val}", "source": "{compthread}"}, {"target": "{write_val}", "source": "{compthread}"}, {"target": "{write_val}", "source": "{compthread}"}, {"target": "{write_val}", "source": "{compthread}"}, {"target": "{write_val}", "source": "{compthread}"}, {"target": "{write_val}", "source": "{compthread}"}, {"target": "{write_val}", "source": "{compthread}"}, {"target": "{write_val}", "source": "{compthread}"}, {"target": "{setpriority}", "source": "{compthread}"}, {"target": "{cond_broadcast}", "source": "{compthread}"}, {"target": "{failure}", "source": "{compthread}"}, {"target": "{failure}", "source": "{compthread}"}, {"target": "{fatal}", "source": "{compthread}"}, {"target": "{fatal}", "source": "{compthread}"}, {"target": "{fatal}", "source": "{compthread}"}, {"target": "{fatal}", "source": "{compthread}"}, {"target": "{fatal}", "source": "{compthread}"}, {"target": "{fatal}", "source": "{compthread}"}, {"target": "{fatal}", "source": "{compthread}"}, {"target": "{fatal}", "source": "{compthread}"}, {"target": "{fatal}", "source": "{compthread}"}, {"target": "{print_err}", "source": "{compthread}"}, {"target": "{print_err}", "source": "{compthread}"}, {"target": "{flush_tmpoutbuf}", "source": "{compthread}"}, {"target": "{zpaq_compress_buf}", "source": "{compthread}"}, {"target": "{lzma_compress_buf}", "source": "{compthread}"}, {"target": "{rewrite_encrypted}", "source": "{compthread}"}, {"target": "{fsync}", "source": "{compthread}"}, {"target": "Node0x214ff80", "source": "{close_tmpinbuf}"}, {"target": "{free}", "source": "{close_stream_in}"}, {"target": "{free}", "source": "{close_stream_in}"}, {"target": "{free}", "source": "{close_stream_in}"}, {"target": "{free}", "source": "{close_stream_in}"}, {"target": "{free}", "source": "{close_stream_in}"}, {"target": "{print_stuff}", "source": "{close_stream_in}"}, {"target": "{get_readseek}", "source": "{close_stream_in}"}, {"target": "{read_seekto}", "source": "{close_stream_in}"}, {"target": "Node0x214ff80", "source": "{perror}"}, {"target": "{free}", "source": "{rewrite_encrypted}"}, {"target": "{free}", "source": "{rewrite_encrypted}"}, {"target": "{fatal}", "source": "{rewrite_encrypted}"}, {"target": "{write_buf}", "source": "{rewrite_encrypted}"}, {"target": "{write_buf}", "source": "{rewrite_encrypted}"}, {"target": "{get_rand}", "source": "{rewrite_encrypted}"}, {"target": "{seekto}", "source": "{rewrite_encrypted}"}, {"target": "{seekto}", "source": "{rewrite_encrypted}"}, {"target": "{seekto}", "source": "{rewrite_encrypted}"}, {"target": "{read_buf}", "source": "{rewrite_encrypted}"}, {"target": "{malloc}", "source": "{rewrite_encrypted}"}, {"target": "{lrz_encrypt}", "source": "{rewrite_encrypted}"}, {"target": "{get_seek}", "source": "{rewrite_encrypted}"}, {"target": "{failure}", "source": "{rewrite_encrypted}"}, {"target": "{failure}", "source": "{rewrite_encrypted}"}, {"target": "{failure}", "source": "{rewrite_encrypted}"}, {"target": "{failure}", "source": "{rewrite_encrypted}"}, {"target": "{failure}", "source": "{rewrite_encrypted}"}, {"target": "{print_err}", "source": "{read_seekto}"}, {"target": "{read_fdin}", "source": "{read_seekto}"}, {"target": "{fd_seekto}", "source": "{read_seekto}"}, {"target": "{dump_stdin}", "source": "{read_seekto}"}]}